README.md
setup.cfg
setup.py
Noisemap/Noisemap.py
Noisemap/__init__.py
Noisemap.egg-info/PKG-INFO
Noisemap.egg-info/SOURCES.txt
Noisemap.egg-info/dependency_links.txt
Noisemap.egg-info/top_level.txt