Metadata-Version: 2.1
Name: Noisemap
Version: 1.0
Summary: A simple library to generate noisemaps.
Home-page: https://hyperhamster535.github.io/Noisemap/
Author: Proximas
Author-email: hyperhamster534@outlook.com
License: UNKNOWN
Platform: UNKNOWN
Classifier: Programming Language :: Python :: 3
Classifier: License :: OSI Approved :: MIT License
Classifier: Operating System :: OS Independent
